pythpy/__init__.py
pythpy/constants.py
pythpy/layouts.py
pythpy/calls/__init__.py
pythpy/calls/async.py
pythpy/calls/sync.py
pythpy/state/__init__.py
pythpy/state/core.py
pythpy/state/oracle.py
pyth_py-0.0.2.dist-info/LICENSE
pyth_py-0.0.2.dist-info/METADATA
pyth_py-0.0.2.dist-info/WHEEL
pyth_py-0.0.2.dist-info/top_level.txt
pyth_py-0.0.2.dist-info/RECORD
