Metadata-Version: 2.1
Name: pyth-py
Version: 0.0.2
Summary: A basic framework for interacting with Solana's Pyth network
Home-page: https://github.com/johnstonematt/pythpy
Author: Matthew Johnstone
Author-email: johnstone.mattjames@gmail.com
License: MIT
Platform: UNKNOWN
Classifier: License :: OSI Approved :: MIT License
Classifier: Programming Language :: Python :: 3
Classifier: Programming Language :: Python :: 3.7
Requires-Dist: solana (>=0.16.0)
